README.txt
setup.cfg
setup.py
repoze/__init__.py
repoze.mailin.egg-info/PKG-INFO
repoze.mailin.egg-info/SOURCES.txt
repoze.mailin.egg-info/dependency_links.txt
repoze.mailin.egg-info/entry_points.txt
repoze.mailin.egg-info/namespace_packages.txt
repoze.mailin.egg-info/not-zip-safe
repoze.mailin.egg-info/requires.txt
repoze.mailin.egg-info/top_level.txt
repoze/mailin/__init__.py
repoze/mailin/interfaces.py
repoze/mailin/maildir.py
repoze/mailin/pending.py
repoze/mailin/scripts/__init__.py
repoze/mailin/scripts/draino.py
repoze/mailin/scripts/pollster.py
repoze/mailin/tests/__init__.py
repoze/mailin/tests/test_maildir.py
repoze/mailin/tests/test_pending.py